halsteadpp/__init__.py
halsteadpp/parsedcode.py
halsteadpp/objects/__init__.py
halsteadpp/objects/function.py
halsteadpp/utils/__init__.py
halsteadpp/utils/halcal.py
halsteadpp-0.1.1.dist-info/METADATA
halsteadpp-0.1.1.dist-info/WHEEL
halsteadpp-0.1.1.dist-info/entry_points.txt
halsteadpp-0.1.1.dist-info/top_level.txt
halsteadpp-0.1.1.dist-info/RECORD
