Metadata-Version: 2.4
Name: halsteadpp
Version: 0.1.1
Summary: A Python tool for analyzing C code complexity using Halstead and Cyclomatic metrics.
Author-email: Arthur Morgado Teixeira <arthurmorgado7751@gmail.com>
License: MIT License
Project-URL: Homepage, https://github.com/Morgadineo/Halsteadpp
Project-URL: Issues, https://github.com/Morgadineo/Halsteadpp/issues
Keywords: halstead,complexity,metrics,c-code,pycparser,rich
Requires-Python: >=3.9
Requires-Dist: pycparser>=2.21
Requires-Dist: rich>=13.0.0
Provides-Extra: dev
Requires-Dist: pytest>=7.0; extra == "dev"
Requires-Dist: black; extra == "dev"
Requires-Dist: flake8; extra == "dev"
